LICENSE.txt
MANIFEST.in
README.md
requirements.txt
setup.cfg
setup.py
revolve/__init__.py
revolve/config.py
revolve/defaults.py
revolve/loss.py
revolve/model.py
revolve/prompts.py
revolve/py.typed
revolve/variable.py
revolve.egg-info/PKG-INFO
revolve.egg-info/SOURCES.txt
revolve.egg-info/dependency_links.txt
revolve.egg-info/not-zip-safe
revolve.egg-info/requires.txt
revolve.egg-info/top_level.txt
revolve/autograd/__init__.py
revolve/autograd/algebra.py
revolve/autograd/function.py
revolve/autograd/functional.py
revolve/autograd/llm_backward_prompts.py
revolve/autograd/llm_ops.py
revolve/autograd/multimodal_backward_prompts.py
revolve/autograd/multimodal_ops.py
revolve/autograd/reduce_prompts.py
revolve/autograd/string_based_ops.py
revolve/engine/__init__.py
revolve/engine/anthropic.py
revolve/engine/base.py
revolve/engine/cohere.py
revolve/engine/engine_utils.py
revolve/engine/gemini.py
revolve/engine/groq.py
revolve/engine/llama3_1.py
revolve/engine/local_model_openai_api.py
revolve/engine/openai.py
revolve/engine/together.py
revolve/engine/vllm.py
revolve/optimizer/__init__.py
revolve/optimizer/optimizer.py
revolve/optimizer/optimizer_prompts.py
revolve/optimizer/optimizer_prompts_v2.py
revolve/optimizer/optimizer_v2.py
revolve/tasks/__init__.py
revolve/tasks/base.py
revolve/tasks/big_bench_hard.py
revolve/tasks/gpqa.py
revolve/tasks/gsm8k.py
revolve/tasks/leetcode.py
revolve/tasks/mmlu.py
revolve/tasks/multimodal/__init__.py
revolve/tasks/multimodal/mathvista.py
revolve/tasks/multimodal/scienceqa.py