Metadata-Version: 2.1
Name: revolve
Version: 0.1.0
Home-page: https://github.com/Peiyance/REVOLVE
Author: Peiyan Zhang
Author-email: pzhangao@cse.ust.hk
License: MIT license
Classifier: Development Status :: 2 - Pre-Alpha
Classifier: Intended Audience :: Developers
Classifier: License :: OSI Approved :: MIT License
Classifier: Natural Language :: English
Classifier: Programming Language :: Python :: 3.9
Requires-Python: >=3.9
License-File: LICENSE.txt
Requires-Dist: openai>=1.23.6
Requires-Dist: tenacity>=8.2.3
Requires-Dist: python-dotenv>=1.0.0
Requires-Dist: pandas>=1.5.3
Requires-Dist: platformdirs>=3.11.0
Requires-Dist: datasets>=2.14.6
Requires-Dist: diskcache>=5.6.3
Requires-Dist: graphviz>=0.20.3
Requires-Dist: gdown>=5.2.0
Requires-Dist: litellm>=1.49.5
Requires-Dist: pillow
Requires-Dist: httpx
Provides-Extra: vllm
Requires-Dist: vllm; extra == "vllm"
